MANIFEST.in
readme.md
requirements.txt
setup.cfg
setup.py
update_version.py
bomber/__init__.py
bomber/_version.py
bomber/classification.py
bomber/climate.py
bomber/converters.py
bomber/measurements.py
bomber/utilities.py
bomber.egg-info/PKG-INFO
bomber.egg-info/SOURCES.txt
bomber.egg-info/dependency_links.txt
bomber.egg-info/requires.txt
bomber.egg-info/top_level.txt